{
  "baseId": "appP7WUa8sRkhBFaT",
  "tables": {
    "taskForceRoster": {
      "id": "tblvkYagzmhVqY1aE",
      "name": "TASK FORCE ROSTER",
      "primaryView": "PRIMARY ROSTER",
      "views": {
        "primaryRoster": "viwsY7xzbWh8N95Df",
        "nonActive": "viwfb5gPYSVBrpenF",
        "j2": "viwSwZGR7VwJfBe16"
      },
      "fields": {
        "name": "Name",
        "rank": "RANK",
        "callsign": "CS",
        "dateOfEnlistment": "DATE OF ENLISTMENT",
        "discordName": "DISCORD NAME",
        "discordId": "DISCORD ID #",
        "steamId": "STEAM ID #",
        "steamProfile": "STEAM PROFILE LINK",
        "timeInService": "TIS",
        "assignedTo": "ASSIGNED TO",
        "status": "STATUS",
        "shop": "SHOP",
        "source": "SOURCE",
        "recruiter": "RECRUITER"
      }
    },
    "sfod": {
      "id": "tblJ7XJknQIGRllYo",
      "name": "1 Troop, A Squadron, 1st SFOD-Delta",
      "fields": {
        "billet": "BILLET",
        "name": "NAME",
        "rank": "RANK",
        "assignedTo": "ASSIGNED TO",
        "timeInService": "TIS",
        "primaryMos": "PRIMARY MOS"
      }
    },
    "rangers": {
      "id": "tblhMjc8r8oFjBPSz",
      "name": "A Co 1/75th RR",
      "fields": {
        "billet": "BILLET",
        "name": "NAME",
        "callsign": "CS",
        "rank": "RANK",
        "platoon": "PLATOON",
        "timeInService": "TIS",
        "primaryMos": "PRIMARY MOS",
        "iet": "IET",
        "fireTeam": "FIRE TEAM",
        "squad": "SQUAD",
        "serverPermissions": "SERVER PERMISSIONS"
      }
    },
    "soar": {
      "id": "tbl84PJ5JxqYg9IG6",
      "name": "B Co 2/160th SOAR",
      "fields": {
        "billet": "BILLET",
        "rank": "RANK",
        "name": "NAME",
        "timeInService": "TIS",
        "primaryMos": "PRIMARY MOS",
        "iet": "IET",
        "platoon": "PLATOON",
        "fireTeam": "FIRE TEAM",
        "squad": "SQUAD"
      }
    },
    "applications": {
      "id": "tblSTOGr0uT44yjkF",
      "name": "ENLISTMENT APPLICATION",
      "fields": {
        "discordId": "DISCORD ID",
        "name": "NAME",
        "discordUserName": "DISCORD USER NAME",
        "source": "SOURCE",
        "priorService": "PRIOR SERVICE",
        "priorArma": "PRIOR ARMA",
        "priorLeadership": "PRIOR LEADERSHIP",
        "interestedUnit": "INTERESTED UNIT",
        "desiredMos": "DESIRED MOS"
      }
    }
  }
}
